pymittagleffler-0.1.8.dist-info/METADATA
pymittagleffler-0.1.8.dist-info/WHEEL
pymittagleffler/__init__.py
pymittagleffler/_bindings.abi3.so
pymittagleffler/_bindings.pyi
pymittagleffler/fallback.py
pymittagleffler/py.typed
pymittagleffler-0.1.8.dist-info/RECORD
