Metadata-Version: 2.4
Name: pymittagleffler
Version: 0.1.8
Classifier: Development Status :: 3 - Alpha
Classifier: Intended Audience :: Developers
Classifier: Intended Audience :: Science/Research
Classifier: Natural Language :: English
Classifier: Programming Language :: Python :: 3 :: Only
Classifier: Programming Language :: Python :: 3.10
Classifier: Programming Language :: Python :: 3.11
Classifier: Programming Language :: Python :: 3.12
Classifier: Programming Language :: Python :: 3.13
Classifier: Programming Language :: Python :: 3.14
Classifier: Programming Language :: Rust
Classifier: Topic :: Scientific/Engineering
Classifier: Topic :: Utilities
Requires-Dist: numpy>=2
Requires-Dist: pyproject-fmt ; extra == 'dev'
Requires-Dist: reuse ; extra == 'dev'
Requires-Dist: typos ; extra == 'dev'
Requires-Dist: uv ; extra == 'dev'
Requires-Dist: sphinx>=6 ; extra == 'docs'
Requires-Dist: sphinx-book-theme ; extra == 'docs'
Requires-Dist: mypy ; extra == 'test'
Requires-Dist: pytest ; extra == 'test'
Requires-Dist: ruff ; extra == 'test'
Provides-Extra: dev
Provides-Extra: docs
Provides-Extra: test
Summary: High performance implementation of the Mittag-Leffler function
Keywords: fractional-calculus,special-functions
Home-Page: https://github.com/alexfikl/mittagleffler
Author-email: Alexandru Fikl <alexfikl@gmail.com>
Maintainer-email: Alexandru Fikl <alexfikl@gmail.com>
License-Expression: MIT
Requires-Python: >=3.10
Project-URL: Documentation, https://mittagleffler.readthedocs.io
Project-URL: Repository, https://github.com/alexfikl/mittagleffler
